niklaus_2019_zxmtools01/__init__.py
niklaus_2019_zxmtools01/get_data.py
niklaus_2019_zxmtools01-0.0.2.dist-info/LICENSE
niklaus_2019_zxmtools01-0.0.2.dist-info/METADATA
niklaus_2019_zxmtools01-0.0.2.dist-info/WHEEL
niklaus_2019_zxmtools01-0.0.2.dist-info/top_level.txt
niklaus_2019_zxmtools01-0.0.2.dist-info/RECORD
