Metadata-Version: 2.1
Name: niklaus_2019_zxmtools01
Version: 0.0.2
Summary: A small example package
Author-email: niklaus <598467866@qq.com>
Project-URL: Homepage, https://github.com/pypa/sampleproject
Project-URL: Bug Tracker, https://github.com/pypa/sampleproject/issues
Classifier: Programming Language :: Python :: 3
Classifier: License :: OSI Approved :: MIT License
Classifier: Operating System :: OS Independent
Requires-Python: >=3.7
License-File: LICENSE
Requires-Dist: setuptools >=65.5.0
